implementation/__init__.py
implementation/model.py
implementation/model_builder.py
inference_worker/__init__.py
inference_worker/cli.py
inference_worker/boilerplate/.env
inference_worker/boilerplate/config.json
inference_worker/boilerplate/implementation/__init__.py
inference_worker/boilerplate/implementation/model.py
inference_worker/boilerplate/implementation/model_builder.py
inference_worker/core/__init__.py
inference_worker/core/abstraction.py
inference_worker/core/exceptions.py
inference_worker/core/handler.py
inference_worker/core/input.py
inference_worker/core/logging.py
inference_worker/core/storage.py
inference_worker/core/utils.py
inference_worker/core/worker.py
inference_worker-0.12.0.dist-info/METADATA
inference_worker-0.12.0.dist-info/WHEEL
inference_worker-0.12.0.dist-info/entry_points.txt
inference_worker-0.12.0.dist-info/top_level.txt
inference_worker-0.12.0.dist-info/RECORD
