Metadata-Version: 2.1
Name: inference-worker
Version: 0.12.0
Summary: A package to handle ML model inference tasks.
Home-page: https://github.com/yourusername/inference_worker
Author: Your Name
Author-email: your.email@example.com
Classifier: Programming Language :: Python :: 3
Classifier: License :: OSI Approved :: MIT License
Classifier: Operating System :: OS Independent
Classifier: Intended Audience :: Developers
Classifier: Topic :: Software Development :: Libraries :: Python Modules
Classifier: Topic :: Scientific/Engineering :: Artificial Intelligence
Requires-Python: >=3.6
Requires-Dist: pika
Requires-Dist: requests
Requires-Dist: click
Requires-Dist: python-dotenv
